compound_core/cache.py
compound_core/config.py
compound_core/interfaces.py
compound_core/paths.py
compound_core/registry.py
compound_core/types.py
compound_core-0.1.1.dist-info/METADATA
compound_core-0.1.1.dist-info/WHEEL
compound_core-0.1.1.dist-info/RECORD
