Metadata-Version: 2.4
Name: compound-core
Version: 0.1.1
Summary: Core utilities for Compound System agent infrastructure
Project-URL: Homepage, https://github.com/YourOrg/Compound-System
Project-URL: Repository, https://github.com/YourOrg/Compound-System
Project-URL: Issues, https://github.com/YourOrg/Compound-System/issues
Author-email: Your Organization <maintainers@example.com>
License: MIT
Classifier: Development Status :: 3 - Alpha
Classifier: Intended Audience :: Developers
Classifier: License :: OSI Approved :: MIT License
Classifier: Programming Language :: Python :: 3
Classifier: Programming Language :: Python :: 3.9
Classifier: Programming Language :: Python :: 3.10
Classifier: Programming Language :: Python :: 3.11
Requires-Python: >=3.9
Requires-Dist: aiohttp>=3.9
Requires-Dist: python-dotenv>=1.0
Requires-Dist: pyyaml>=6.0
Provides-Extra: dev
Requires-Dist: pytest-asyncio>=0.21; extra == 'dev'
Requires-Dist: pytest>=7.0; extra == 'dev'
